sheetgear/__init__.py
sheetgear/__main__.py
sheetgear/bridge/__init__.py
sheetgear/bridge/client.py
sheetgear/bridge/errors.py
sheetgear/bridge/gauth.py
sheetgear/bridge/utils.py
sheetgear/bridge/xargs.py
sheetgear_bridge-0.1.0.dist-info/LICENSE.txt
sheetgear_bridge-0.1.0.dist-info/METADATA
sheetgear_bridge-0.1.0.dist-info/WHEEL
sheetgear_bridge-0.1.0.dist-info/top_level.txt
sheetgear_bridge-0.1.0.dist-info/RECORD
