Metadata-Version: 2.1
Name: sheetgear-bridge
Version: 0.1.0
Summary: UNKNOWN
Home-page: https://github.com/sheetgear/sheetgear-bridge
Author: sheetgear
Author-email: sheetgear@gmail.com
License: GPL-3.0
Download-URL: https://github.com/sheetgear/sheetgear-bridge/downloads
Keywords: sheetgear
Platform: UNKNOWN
Classifier: Programming Language :: Python :: 3
Classifier: Operating System :: OS Independent
Requires-Dist: google-api-python-client
Requires-Dist: google-auth-httplib2
Requires-Dist: google-auth-oauthlib
